Workbook
Name Commision_Tiers: Table3[#All]
Name Managers: Table4[#All]
Name Managers_Table: Table4[]
Name NativeTimeline_Payment_day: #N/A
Name Orders: Sales_Data_Analysis[#All]
Name Sales_Data: Sales_Data_Analysis!$A$1:$M$57
Name Slicer_Category: #N/A

Sheet Sales_Data_Analysis
A1: Order_ID | B1: Order_Date | C1: Monnth | D1: Year | E1: Delivery_Date | F1: Country_Region | G1: Country | H1: Region | I1: Category | J1: Product_Name | K1: Cost | L1: Gross_Sales | M1: Profit | N1: Status | O1: Commision | P1: Payment_day | Q1: Days_to _deliver
A2: ORD-002 | B2: 2018-07-31 | C2: =MONTH(Sales_Data_Analysis[[#This Row],[Order_Date]]) -> 7 | D2: =YEAR(Sales_Data_Analysis[[#This Row],[Order_Date]]) -> 2018 | E2: 43324 | F2: UK (Europe) | G2: UK | H2: Europe | I2: PCs | J2: Dell Inspiron | K2: 557 | L2: 952 | M2: =IFERROR(Sales_Data_Analysis[[#This Row],[Gross_Sales]]-Sales_Data_Analysis[[#This Row],[Cost]],"No data") -> 395 | N2: =IF(Sales_Data_Analysis[[#This Row],[Profit]]<=Reference_Tables!$F$7,Reference_Tables!$G$7,IF(Sales_Data_Analysis[[#This Row],[Profit]]<=Reference_Tables!$F$6,Reference_Tables!$G$6,IF(Sales_Data_Analysis[[#This Row],[Profit]]<=Reference_Tables!$F$5,Reference_Tables!$G$5,Reference_Tables!$G$4))) -> Gold | O2: =VLOOKUP(Sales_Data_Analysis[[#This Row],[Gross_Sales]],Table3[],2,TRUE) -> 0.02 | P2: =EOMONTH(Sales_Data_Analysis[[#This Row],[Order_Date]],1) -> 43343 | Q2: =NETWORKDAYS(Sales_Data_Analysis[[#This Row],[Order_Date]],Sales_Data_Analysis[[#This Row],[Delivery_Date]]) -> 9 | S2: Project | T2: Manager
A3: ORD-004 | B3: 2019-07-01 | C3: =MONTH(Sales_Data_Analysis[[#This Row],[Order_Date]]) -> 7 | D3: =YEAR(Sales_Data_Analysis[[#This Row],[Order_Date]]) -> 2019 | E3: 43657 | F3: Poland (Europe) | G3: Poland | H3: Europe | I3: Mobile Phones | J3: Samsung Galaxy S23 | K3: 931 | L3: 1604 | M3: =IFERROR(Sales_Data_Analysis[[#This Row],[Gross_Sales]]-Sales_Data_Analysis[[#This Row],[Cost]],"No data") -> 673 | N3: =IF(Sales_Data_Analysis[[#This Row],[Profit]]<=Reference_Tables!$F$7,Reference_Tables!$G$7,IF(Sales_Data_Analysis[[#This Row],[Profit]]<=Reference_Tables!$F$6,Reference_Tables!$G$6,IF(Sales_Data_Analysis[[#This Row],[Profit]]<=Reference_Tables!$F$5,Reference_Tables!$G$5,Reference_Tables!$G$4))) -> Platinum | O3: =VLOOKUP(Sales_Data_Analysis[[#This Row],[Gross_Sales]],Table3[],2,TRUE) -> 0.1 | P3: =EOMONTH(Sales_Data_Analysis[[#This Row],[Order_Date]],1) -> 43708 | Q3: =NETWORKDAYS(Sales_Data_Analysis[[#This Row],[Order_Date]],Sales_Data_Analysis[[#This Row],[Delivery_Date]]) -> 9 | S3: Microsoft Surface | T3: =_xlfn.IFNA(INDEX(Table4[],MATCH(S3,Table4[Project Managers],0),2),"No manager found") -> Oscar Isaac
A4: ORD-007 | B4: 2018-01-31 | C4: =MONTH(Sales_Data_Analysis[[#This Row],[Order_Date]]) -> 1 | D4: =YEAR(Sales_Data_Analysis[[#This Row],[Order_Date]]) -> 2018 | E4: 43136 | F4: Poland (Europe) | G4: Poland | H4: Europe | I4: Laptops | J4: Lenovo Thinkpad | K4: 999 | L4: 1579 | M4: =IFERROR(Sales_Data_Analysis[[#This Row],[Gross_Sales]]-Sales_Data_Analysis[[#This Row],[Cost]],"No data") -> 580 | N4: =IF(Sales_Data_Analysis[[#This Row],[Profit]]<=Reference_Tables!$F$7,Reference_Tables!$G$7,IF(Sales_Data_Analysis[[#This Row],[Profit]]<=Reference_Tables!$F$6,Reference_Tables!$G$6,IF(Sales_Data_Analysis[[#This Row],[Profit]]<=Reference_Tables!$F$5,Reference_Tables!$G$5,Reference_Tables!$G$4))) -> Gold | O4: =VLOOKUP(Sales_Data_Analysis[[#This Row],[Gross_Sales]],Table3[],2,TRUE) -> 0.1 | P4: =EOMONTH(Sales_Data_Analysis[[#This Row],[Order_Date]],1) -> 43159 | Q4: =NETWORKDAYS(Sales_Data_Analysis[[#This Row],[Order_Date]],Sales_Data_Analysis[[#This Row],[Delivery_Date]]) -> 4
A5: ORD-010 | B5: 2018-02-13 | C5: =MONTH(Sales_Data_Analysis[[#This Row],[Order_Date]]) -> 2 | D5: =YEAR(Sales_Data_Analysis[[#This Row],[Order_Date]]) -> 2018 | E5: 43153 | F5: USA (North America) | G5: USA | H5: North America | I5: Laptops | J5: Dell Xps 15 | K5: 382 | L5: 1007 | M5: =IFERROR(Sales_Data_Analysis[[#This Row],[Gross_Sales]]-Sales_Data_Analysis[[#This Row],[Cost]],"No data") -> 625 | N5: =IF(Sales_Data_Analysis[[#This Row],[Profit]]<=Reference_Tables!$F$7,Reference_Tables!$G$7,IF(Sales_Data_Analysis[[#This Row],[Profit]]<=Reference_Tables!$F$6,Reference_Tables!$G$6,IF(Sales_Data_Analysis[[#This Row],[Profit]]<=Reference_Tables!$F$5,Reference_Tables!$G$5,Reference_Tables!$G$4))) -> Platinum | O5: =VLOOKUP(Sales_Data_Analysis[[#This Row],[Gross_Sales]],Table3[],2,TRUE) -> 0.05 | P5: =EOMONTH(Sales_Data_Analysis[[#This Row],[Order_Date]],1) -> 43190 | Q5: =NETWORKDAYS(Sales_Data_Analysis[[#This Row],[Order_Date]],Sales_Data_Analysis[[#This Row],[Delivery_Date]]) -> 8
A6: ORD-012 | B6: 2018-06-14 | C6: =MONTH(Sales_Data_Analysis[[#This Row],[Order_Date]]) -> 6 | D6: =YEAR(Sales_Data_Analysis[[#This Row],[Order_Date]]) -> 2018 | E6: 43279 | F6: France (Europe) | G6: France | H6: Europe | I6: Accessories | J6: Keychron Keyboard | K6: 500 | L6: 922 | M6: =IFERROR(Sales_Data_Analysis[[#This Row],[Gross_Sales]]-Sales_Data_Analysis[[#This Row],[Cost]],"No data") -> 422 | N6: =IF(Sales_Data_Analysis[[#This Row],[Profit]]<=Reference_Tables!$F$7,Reference_Tables!$G$7,IF(Sales_Data_Analysis[[#This Row],[Profit]]<=Reference_Tables!$F$6,Reference_Tables!$G$6,IF(Sales_Data_Analysis[[#This Row],[Profit]]<=Reference_Tables!$F$5,Reference_Tables!$G$5,Reference_Tables!$G$4))) -> Gold | O6: =VLOOKUP(Sales_Data_Analysis[[#This Row],[Gross_Sales]],Table3[],2,TRUE) -> 0.02 | P6: =EOMONTH(Sales_Data_Analysis[[#This Row],[Order_Date]],1) -> 43312 | Q6: =NETWORKDAYS(Sales_Data_Analysis[[#This Row],[Order_Date]],Sales_Data_Analysis[[#This Row],[Delivery_Date]]) -> 11
A7: ORD-014 | B7: 2018-05-17 | C7: =MONTH(Sales_Data_Analysis[[#This Row],[Order_Date]]) -> 5 | D7: =YEAR(Sales_Data_Analysis[[#This Row],[Order_Date]]) -> 2018 | E7: 43240 | F7: France (Europe) | G7: France | H7: Europe | I7: Accessories | J7: Keychron Keyboard | K7: 904 | L7: 1152 | M7: =IFERROR(Sales_Data_Analysis[[#This Row],[Gross_Sales]]-Sales_Data_Analysis[[#This Row],[Cost]],"No data") -> 248 | N7: =IF(Sales_Data_Analysis[[#This Row],[Profit]]<=Reference_Tables!$F$7,Reference_Tables!$G$7,IF(Sales_Data_Analysis[[#This Row],[Profit]]<=Reference_Tables!$F$6,Reference_Tables!$G$6,IF(Sales_Data_Analysis[[#This Row],[Profit]]<=Reference_Tables!$F$5,Reference_Tables!$G$5,Reference_Tables!$G$4))) -> Silver | O7: =VLOOKUP(Sales_Data_Analysis[[#This Row],[Gross_Sales]],Table3[],2,TRUE) -> 0.05 | P7: =EOMONTH(Sales_Data_Analysis[[#This Row],[Order_Date]],1) -> 43281 | Q7: =NETWORKDAYS(Sales_Data_Analysis[[#This Row],[Order_Date]],Sales_Data_Analysis[[#This Row],[Delivery_Date]]) -> 2
A8: ORD-017 | B8: 2019-06-18 | C8: =MONTH(Sales_Data_Analysis[[#This Row],[Order_Date]]) -> 6 | D8: =YEAR(Sales_Data_Analysis[[#This Row],[Order_Date]]) -> 2019 | E8: 43647 | F8: France (Europe) | G8: France | H8: Europe | I8: Tablets | J8: Ipad Pro | K8: 768 | L8: 1186 | M8: =IFERROR(Sales_Data_Analysis[[#This Row],[Gross_Sales]]-Sales_Data_Analysis[[#This Row],[Cost]],"No data") -> 418 | N8: =IF(Sales_Data_Analysis[[#This Row],[Profit]]<=Reference_Tables!$F$7,Reference_Tables!$G$7,IF(Sales_Data_Analysis[[#This Row],[Profit]]<=Reference_Tables!$F$6,Reference_Tables!$G$6,IF(Sales_Data_Analysis[[#This Row],[Profit]]<=Reference_Tables!$F$5,Reference_Tables!$G$5,Reference_Tables!$G$4))) -> Gold | O8: =VLOOKUP(Sales_Data_Analysis[[#This Row],[Gross_Sales]],Table3[],2,TRUE) -> 0.05 | P8: =EOMONTH(Sales_Data_Analysis[[#This Row],[Order_Date]],1) -> 43677 | Q8: =NETWORKDAYS(Sales_Data_Analysis[[#This Row],[Order_Date]],Sales_Data_Analysis[[#This Row],[Delivery_Date]]) -> 10
A9: ORD-018 | B9: 2019-02-14 | C9: =MONTH(Sales_Data_Analysis[[#This Row],[Order_Date]]) -> 2 | D9: =YEAR(Sales_Data_Analysis[[#This Row],[Order_Date]]) -> 2019 | E9: 43520 | F9: India (Asia) | G9: India | H9: Asia | I9: Mobile Phones | J9: Oneplus 11 | K9: 416 | L9: 896 | M9: =IFERROR(Sales_Data_Analysis[[#This Row],[Gross_Sales]]-Sales_Data_Analysis[[#This Row],[Cost]],"No data") -> 480 | N9: =IF(Sales_Data_Analysis[[#This Row],[Profit]]<=Reference_Tables!$F$7,Reference_Tables!$G$7,IF(Sales_Data_Analysis[[#This Row],[Profit]]<=Reference_Tables!$F$6,Reference_Tables!$G$6,IF(Sales_Data_Analysis[[#This Row],[Profit]]<=Reference_Tables!$F$5,Reference_Tables!$G$5,Reference_Tables!$G$4))) -> Gold | O9: =VLOOKUP(Sales_Data_Analysis[[#This Row],[Gross_Sales]],Table3[],2,TRUE) -> 0.02 | P9: =EOMONTH(Sales_Data_Analysis[[#This Row],[Order_Date]],1) -> 43555 | Q9: =NETWORKDAYS(Sales_Data_Analysis[[#This Row],[Order_Date]],Sales_Data_Analysis[[#This Row],[Delivery_Date]]) -> 7
A10: ORD-019 | B10: 2018-12-09 | C10: =MONTH(Sales_Data_Analysis[[#This Row],[Order_Date]]) -> 12 | D10: =YEAR(Sales_Data_Analysis[[#This Row],[Order_Date]]) -> 2018 | E10: 43451 | F10: Canada (North America) | G10: Canada | H10: North America | I10: Mobile Phones | J10: Oneplus 11 | K10: 953 | L10: 1411 | M10: =IFERROR(Sales_Data_Analysis[[#This Row],[Gross_Sales]]-Sales_Data_Analysis[[#This Row],[Cost]],"No data") -> 458 | N10: =IF(Sales_Data_Analysis[[#This Row],[Profit]]<=Reference_Tables!$F$7,Reference_Tables!$G$7,IF(Sales_Data_Analysis[[#This Row],[Profit]]<=Reference_Tables!$F$6,Reference_Tables!$G$6,IF(Sales_Data_Analysis[[#This Row],[Profit]]<=Reference_Tables!$F$5,Reference_Tables!$G$5,Reference_Tables!$G$4))) -> Gold | O10: =VLOOKUP(Sales_Data_Analysis[[#This Row],[Gross_Sales]],Table3[],2,TRUE) -> 0.05 | P10: =EOMONTH(Sales_Data_Analysis[[#This Row],[Order_Date]],1) -> 43496 | Q10: =NETWORKDAYS(Sales_Data_Analysis[[#This Row],[Order_Date]],Sales_Data_Analysis[[#This Row],[Delivery_Date]]) -> 6
A11: ORD-021 | B11: 2018-09-14 | C11: =MONTH(Sales_Data_Analysis[[#This Row],[Order_Date]]) -> 9 | D11: =YEAR(Sales_Data_Analysis[[#This Row],[Order_Date]]) -> 2018 | E11: 43367 | F11: Poland (Europe) | G11: Poland | H11: Europe | I11: Mobile Phones | J11: Google Pixel 7 | K11: 483 | L11: 825 | M11: =IFERROR(Sales_Data_Analysis[[#This Row],[Gross_Sales]]-Sales_Data_Analysis[[#This Row],[Cost]],"No data") -> 342 | N11: =IF(Sales_Data_Analysis[[#This Row],[Profit]]<=Reference_Tables!$F$7,Reference_Tables!$G$7,IF(Sales_Data_Analysis[[#This Row],[Profit]]<=Reference_Tables!$F$6,Reference_Tables!$G$6,IF(Sales_Data_Analysis[[#This Row],[Profit]]<=Reference_Tables!$F$5,Reference_Tables!$G$5,Reference_Tables!$G$4))) -> Gold | O11: =VLOOKUP(Sales_Data_Analysis[[#This Row],[Gross_Sales]],Table3[],2,TRUE) -> 0.02 | P11: =EOMONTH(Sales_Data_Analysis[[#This Row],[Order_Date]],1) -> 43404 | Q11: =NETWORKDAYS(Sales_Data_Analysis[[#This Row],[Order_Date]],Sales_Data_Analysis[[#This Row],[Delivery_Date]]) -> 7
A12: ORD-022 | B12: 2018-06-22 | C12: =MONTH(Sales_Data_Analysis[[#This Row],[Order_Date]]) -> 6 | D12: =YEAR(Sales_Data_Analysis[[#This Row],[Order_Date]]) -> 2018 | E12: 43282 | F12: France (Europe) | G12: France | H12: Europe | I12: Accessories | J12: Apple Airpods | K12: 334 | L12: 981 | M12: =IFERROR(Sales_Data_Analysis[[#This Row],[Gross_Sales]]-Sales_Data_Analysis[[#This Row],[Cost]],"No data") -> 647 | N12: =IF(Sales_Data_Analysis[[#This Row],[Profit]]<=Reference_Tables!$F$7,Reference_Tables!$G$7,IF(Sales_Data_Analysis[[#This Row],[Profit]]<=Reference_Tables!$F$6,Reference_Tables!$G$6,IF(Sales_Data_Analysis[[#This Row],[Profit]]<=Reference_Tables!$F$5,Reference_Tables!$G$5,Reference_Tables!$G$4))) -> Platinum | O12: =VLOOKUP(Sales_Data_Analysis[[#This Row],[Gross_Sales]],Table3[],2,TRUE) -> 0.02 | P12: =EOMONTH(Sales_Data_Analysis[[#This Row],[Order_Date]],1) -> 43312 | Q12: =NETWORKDAYS(Sales_Data_Analysis[[#This Row],[Order_Date]],Sales_Data_Analysis[[#This Row],[Delivery_Date]]) -> 6
A13: ORD-023 | B13: 2018-06-22 | C13: =MONTH(Sales_Data_Analysis[[#This Row],[Order_Date]]) -> 6 | D13: =YEAR(Sales_Data_Analysis[[#This Row],[Order_Date]]) -> 2018 | E13: 43285 | F13: Poland (Europe) | G13: Poland | H13: Europe | I13: PCs | J13: Dell Inspiron | K13: 472 | L13: 785 | M13: =IFERROR(Sales_Data_Analysis[[#This Row],[Gross_Sales]]-Sales_Data_Analysis[[#This Row],[Cost]],"No data") -> 313 | N13: =IF(Sales_Data_Analysis[[#This Row],[Profit]]<=Reference_Tables!$F$7,Reference_Tables!$G$7,IF(Sales_Data_Analysis[[#This Row],[Profit]]<=Reference_Tables!$F$6,Reference_Tables!$G$6,IF(Sales_Data_Analysis[[#This Row],[Profit]]<=Reference_Tables!$F$5,Reference_Tables!$G$5,Reference_Tables!$G$4))) -> Gold | O13: =VLOOKUP(Sales_Data_Analysis[[#This Row],[Gross_Sales]],Table3[],2,TRUE) -> 0.02 | P13: =EOMONTH(Sales_Data_Analysis[[#This Row],[Order_Date]],1) -> 43312 | Q13: =NETWORKDAYS(Sales_Data_Analysis[[#This Row],[Order_Date]],Sales_Data_Analysis[[#This Row],[Delivery_Date]]) -> 9
A14: ORD-026 | B14: 2019-06-28 | C14: =MONTH(Sales_Data_Analysis[[#This Row],[Order_Date]]) -> 6 | D14: =YEAR(Sales_Data_Analysis[[#This Row],[Order_Date]]) -> 2019 | E14: 43647 | F14: China (Asia) | G14: China | H14: Asia | I14: PCs | J14: Lenovo Legion | K14: 148 | L14: 451 | M14: =IFERROR(Sales_Data_Analysis[[#This Row],[Gross_Sales]]-Sales_Data_Analysis[[#This Row],[Cost]],"No data") -> 303 | N14: =IF(Sales_Data_Analysis[[#This Row],[Profit]]<=Reference_Tables!$F$7,Reference_Tables!$G$7,IF(Sales_Data_Analysis[[#This Row],[Profit]]<=Reference_Tables!$F$6,Reference_Tables!$G$6,IF(Sales_Data_Analysis[[#This Row],[Profit]]<=Reference_Tables!$F$5,Reference_Tables!$G$5,Reference_Tables!$G$4))) -> Gold | O14: =VLOOKUP(Sales_Data_Analysis[[#This Row],[Gross_Sales]],Table3[],2,TRUE) -> 0 | P14: =EOMONTH(Sales_Data_Analysis[[#This Row],[Order_Date]],1) -> 43677 | Q14: =NETWORKDAYS(Sales_Data_Analysis[[#This Row],[Order_Date]],Sales_Data_Analysis[[#This Row],[Delivery_Date]]) -> 2
A15: ORD-027 | B15: 2019-11-23 | C15: =MONTH(Sales_Data_Analysis[[#This Row],[Order_Date]]) -> 11 | D15: =YEAR(Sales_Data_Analysis[[#This Row],[Order_Date]]) -> 2019 | E15: 43802 | F15: India (Asia) | G15: India | H15: Asia | I15: PCs | J15: Custom Pc Build | K15: 766 | L15: 1054 | M15: =IFERROR(Sales_Data_Analysis[[#This Row],[Gross_Sales]]-Sales_Data_Analysis[[#This Row],[Cost]],"No data") -> 288 | N15: =IF(Sales_Data_Analysis[[#This Row],[Profit]]<=Reference_Tables!$F$7,Reference_Tables!$G$7,IF(Sales_Data_Analysis[[#This Row],[Profit]]<=Reference_Tables!$F$6,Reference_Tables!$G$6,IF(Sales_Data_Analysis[[#This Row],[Profit]]<=Reference_Tables!$F$5,Reference_Tables!$G$5,Reference_Tables!$G$4))) -> Silver | O15: =VLOOKUP(Sales_Data_Analysis[[#This Row],[Gross_Sales]],Table3[],2,TRUE) -> 0.05 | P15: =EOMONTH(Sales_Data_Analysis[[#This Row],[Order_Date]],1) -> 43830 | Q15: =NETWORKDAYS(Sales_Data_Analysis[[#This Row],[Order_Date]],Sales_Data_Analysis[[#This Row],[Delivery_Date]]) -> 7
... A56: ORD-120 | B56: 2018-02-15 | C56: =MONTH(Sales_Data_Analysis[[#This Row],[Order_Date]]) -> 2 | D56: =YEAR(Sales_Data_Analysis[[#This Row],[Order_Date]]) -> 2018 | E56: 43158 | F56: France (Europe) | G56: France | H56: Europe | I56: Laptops | J56: Dell Xps 15 | K56: 913 | L56: 1351 | M56: =IFERROR(Sales_Data_Analysis[[#This Row],[Gross_Sales]]-Sales_Data_Analysis[[#This Row],[Cost]],"No data") -> 438 | N56: =IF(Sales_Data_Analysis[[#This Row],[Profit]]<=Reference_Tables!$F$7,Reference_Tables!$G$7,IF(Sales_Data_Analysis[[#This Row],[Profit]]<=Reference_Tables!$F$6,Reference_Tables!$G$6,IF(Sales_Data_Analysis[[#This Row],[Profit]]<=Reference_Tables!$F$5,Reference_Tables!$G$5,Reference_Tables!$G$4))) -> Gold | O56: =VLOOKUP(Sales_Data_Analysis[[#This Row],[Gross_Sales]],Table3[],2,TRUE) -> 0.05 | P56: =EOMONTH(Sales_Data_Analysis[[#This Row],[Order_Date]],1) -> 43190 | Q56: =NETWORKDAYS(Sales_Data_Analysis[[#This Row],[Order_Date]],Sales_Data_Analysis[[#This Row],[Delivery_Date]]) -> 9
A57: ORD-003 | B57: 2019-08-06 | C57: =MONTH(Sales_Data_Analysis[[#This Row],[Order_Date]]) -> 8 | D57: =YEAR(Sales_Data_Analysis[[#This Row],[Order_Date]]) -> 2019 | E57: 43160 | F57: China (Asia) | G57: China | H57: Asia | I57: Tablets | J57: samsung GALAXY tab | K57: 0 | L57: 654 | M57: 654 | N57: =IF(Sales_Data_Analysis[[#This Row],[Profit]]<=Reference_Tables!$F$7,Reference_Tables!$G$7,IF(Sales_Data_Analysis[[#This Row],[Profit]]<=Reference_Tables!$F$6,Reference_Tables!$G$6,IF(Sales_Data_Analysis[[#This Row],[Profit]]<=Reference_Tables!$F$5,Reference_Tables!$G$5,Reference_Tables!$G$4))) -> Platinum | O57: =VLOOKUP(Sales_Data_Analysis[[#This Row],[Gross_Sales]],Table3[],2,TRUE) -> 0.02 | P57: =EOMONTH(Sales_Data_Analysis[[#This Row],[Order_Date]],1) -> 43738 | Q57: =NETWORKDAYS(Sales_Data_Analysis[[#This Row],[Order_Date]],Sales_Data_Analysis[[#This Row],[Delivery_Date]]) -> -374
A58: ORD-005 | B58: 2019-07-25 | C58: =MONTH(Sales_Data_Analysis[[#This Row],[Order_Date]]) -> 7 | D58: =YEAR(Sales_Data_Analysis[[#This Row],[Order_Date]]) -> 2019 | E58: 43161 | F58: USA (North America) | G58: USA | H58: North America | I58: Tablets | J58: Microsoft SURface | K58: 0 | L58: 1187 | M58: 1187 | N58: =IF(Sales_Data_Analysis[[#This Row],[Profit]]<=Reference_Tables!$F$7,Reference_Tables!$G$7,IF(Sales_Data_Analysis[[#This Row],[Profit]]<=Reference_Tables!$F$6,Reference_Tables!$G$6,IF(Sales_Data_Analysis[[#This Row],[Profit]]<=Reference_Tables!$F$5,Reference_Tables!$G$5,Reference_Tables!$G$4))) -> Diamond | O58: =VLOOKUP(Sales_Data_Analysis[[#This Row],[Gross_Sales]],Table3[],2,TRUE) -> 0.05 | P58: =EOMONTH(Sales_Data_Analysis[[#This Row],[Order_Date]],1) -> 43708 | Q58: =NETWORKDAYS(Sales_Data_Analysis[[#This Row],[Order_Date]],Sales_Data_Analysis[[#This Row],[Delivery_Date]]) -> -365
A59: ORD-006 | B59: 2018-03-28 | C59: =MONTH(Sales_Data_Analysis[[#This Row],[Order_Date]]) -> 3 | D59: =YEAR(Sales_Data_Analysis[[#This Row],[Order_Date]]) -> 2018 | E59: 43162 | F59: Australia (Oceania) | G59: Australia | H59: Oceania | I59: Accessories | J59: apple AIRPODS | K59: 0 | L59: 1241 | M59: 1241 | N59: =IF(Sales_Data_Analysis[[#This Row],[Profit]]<=Reference_Tables!$F$7,Reference_Tables!$G$7,IF(Sales_Data_Analysis[[#This Row],[Profit]]<=Reference_Tables!$F$6,Reference_Tables!$G$6,IF(Sales_Data_Analysis[[#This Row],[Profit]]<=Reference_Tables!$F$5,Reference_Tables!$G$5,Reference_Tables!$G$4))) -> Diamond | O59: =VLOOKUP(Sales_Data_Analysis[[#This Row],[Gross_Sales]],Table3[],2,TRUE) -> 0.05 | P59: =EOMONTH(Sales_Data_Analysis[[#This Row],[Order_Date]],1) -> 43220 | Q59: =NETWORKDAYS(Sales_Data_Analysis[[#This Row],[Order_Date]],Sales_Data_Analysis[[#This Row],[Delivery_Date]]) -> -18
A60: ORD-008 | B60: 2019-09-29 | C60: =MONTH(Sales_Data_Analysis[[#This Row],[Order_Date]]) -> 9 | D60: =YEAR(Sales_Data_Analysis[[#This Row],[Order_Date]]) -> 2019 | E60: 43163 | F60: China (Asia) | G60: China | H60: Asia | I60: Mobile Phones | J60: oneplus 11 | K60: 0 | L60: 360 | M60: 360 | N60: =IF(Sales_Data_Analysis[[#This Row],[Profit]]<=Reference_Tables!$F$7,Reference_Tables!$G$7,IF(Sales_Data_Analysis[[#This Row],[Profit]]<=Reference_Tables!$F$6,Reference_Tables!$G$6,IF(Sales_Data_Analysis[[#This Row],[Profit]]<=Reference_Tables!$F$5,Reference_Tables!$G$5,Reference_Tables!$G$4))) -> Gold | O60: =VLOOKUP(Sales_Data_Analysis[[#This Row],[Gross_Sales]],Table3[],2,TRUE) -> 0 | P60: =EOMONTH(Sales_Data_Analysis[[#This Row],[Order_Date]],1) -> 43769 | Q60: =NETWORKDAYS(Sales_Data_Analysis[[#This Row],[Order_Date]],Sales_Data_Analysis[[#This Row],[Delivery_Date]]) -> -410
A61: ORD-009 | B61: 2018-07-02 | C61: =MONTH(Sales_Data_Analysis[[#This Row],[Order_Date]]) -> 7 | D61: =YEAR(Sales_Data_Analysis[[#This Row],[Order_Date]]) -> 2018 | E61: 43164 | F61: Canada (North America) | G61: Canada | H61: North America | I61: PCs | J61: custom pc build | K61: 0 | L61: 1196 | M61: 1196 | N61: =IF(Sales_Data_Analysis[[#This Row],[Profit]]<=Reference_Tables!$F$7,Reference_Tables!$G$7,IF(Sales_Data_Analysis[[#This Row],[Profit]]<=Reference_Tables!$F$6,Reference_Tables!$G$6,IF(Sales_Data_Analysis[[#This Row],[Profit]]<=Reference_Tables!$F$5,Reference_Tables!$G$5,Reference_Tables!$G$4))) -> Diamond | O61: =VLOOKUP(Sales_Data_Analysis[[#This Row],[Gross_Sales]],Table3[],2,TRUE) -> 0.05 | P61: =EOMONTH(Sales_Data_Analysis[[#This Row],[Order_Date]],1) -> 43343 | Q61: =NETWORKDAYS(Sales_Data_Analysis[[#This Row],[Order_Date]],Sales_Data_Analysis[[#This Row],[Delivery_Date]]) -> -86
A62: ORD-011 | B62: 2018-06-18 | C62: =MONTH(Sales_Data_Analysis[[#This Row],[Order_Date]]) -> 6 | D62: =YEAR(Sales_Data_Analysis[[#This Row],[Order_Date]]) -> 2018 | E62: 43165 | F62: Germany (Europe) | G62: Germany | H62: Europe | I62: Mobile Phones | J62: iPhOnE 14 pro | K62: 0 | L62: 534 | M62: 534 | N62: =IF(Sales_Data_Analysis[[#This Row],[Profit]]<=Reference_Tables!$F$7,Reference_Tables!$G$7,IF(Sales_Data_Analysis[[#This Row],[Profit]]<=Reference_Tables!$F$6,Reference_Tables!$G$6,IF(Sales_Data_Analysis[[#This Row],[Profit]]<=Reference_Tables!$F$5,Reference_Tables!$G$5,Reference_Tables!$G$4))) -> Gold | O62: =VLOOKUP(Sales_Data_Analysis[[#This Row],[Gross_Sales]],Table3[],2,TRUE) -> 0.02 | P62: =EOMONTH(Sales_Data_Analysis[[#This Row],[Order_Date]],1) -> 43312 | Q62: =NETWORKDAYS(Sales_Data_Analysis[[#This Row],[Order_Date]],Sales_Data_Analysis[[#This Row],[Delivery_Date]]) -> -75
A63: ORD-013 | B63: 2019-11-13 | C63: =MONTH(Sales_Data_Analysis[[#This Row],[Order_Date]]) -> 11 | D63: =YEAR(Sales_Data_Analysis[[#This Row],[Order_Date]]) -> 2019 | E63: 43166 | F63: Australia (Oceania) | G63: Australia | H63: Oceania | I63: PCs | J63: Dell INSPIRON | K63: 0 | L63: 862 | M63: 862 | N63: =IF(Sales_Data_Analysis[[#This Row],[Profit]]<=Reference_Tables!$F$7,Reference_Tables!$G$7,IF(Sales_Data_Analysis[[#This Row],[Profit]]<=Reference_Tables!$F$6,Reference_Tables!$G$6,IF(Sales_Data_Analysis[[#This Row],[Profit]]<=Reference_Tables!$F$5,Reference_Tables!$G$5,Reference_Tables!$G$4))) -> Platinum | O63: =VLOOKUP(Sales_Data_Analysis[[#This Row],[Gross_Sales]],Table3[],2,TRUE) -> 0.02 | P63: =EOMONTH(Sales_Data_Analysis[[#This Row],[Order_Date]],1) -> 43830 | Q63: =NETWORKDAYS(Sales_Data_Analysis[[#This Row],[Order_Date]],Sales_Data_Analysis[[#This Row],[Delivery_Date]]) -> -441
A64: ORD-015 | B64: 2018-09-17 | C64: =MONTH(Sales_Data_Analysis[[#This Row],[Order_Date]]) -> 9 | D64: =YEAR(Sales_Data_Analysis[[#This Row],[Order_Date]]) -> 2018 | E64: 43167 | F64: China (Asia) | G64: China | H64: Asia | I64: PCs | J64: Dell INSPIRON | K64: 0 | L64: 1485 | M64: 1485 | N64: =IF(Sales_Data_Analysis[[#This Row],[Profit]]<=Reference_Tables!$F$7,Reference_Tables!$G$7,IF(Sales_Data_Analysis[[#This Row],[Profit]]<=Reference_Tables!$F$6,Reference_Tables!$G$6,IF(Sales_Data_Analysis[[#This Row],[Profit]]<=Reference_Tables!$F$5,Reference_Tables!$G$5,Reference_Tables!$G$4))) -> Diamond | O64: =VLOOKUP(Sales_Data_Analysis[[#This Row],[Gross_Sales]],Table3[],2,TRUE) -> 0.05 | P64: =EOMONTH(Sales_Data_Analysis[[#This Row],[Order_Date]],1) -> 43404 | Q64: =NETWORKDAYS(Sales_Data_Analysis[[#This Row],[Order_Date]],Sales_Data_Analysis[[#This Row],[Delivery_Date]]) -> -138
A65: ORD-016 | B65: 2018-10-25 | C65: =MONTH(Sales_Data_Analysis[[#This Row],[Order_Date]]) -> 10 | D65: =YEAR(Sales_Data_Analysis[[#This Row],[Order_Date]]) -> 2018 | E65: 43168 | F65: Japan (Asia) | G65: Japan | H65: Asia | I65: PCs | J65: hp PAVILION | K65: 0 | L65: 1489 | M65: 1489 | N65: =IF(Sales_Data_Analysis[[#This Row],[Profit]]<=Reference_Tables!$F$7,Reference_Tables!$G$7,IF(Sales_Data_Analysis[[#This Row],[Profit]]<=Reference_Tables!$F$6,Reference_Tables!$G$6,IF(Sales_Data_Analysis[[#This Row],[Profit]]<=Reference_Tables!$F$5,Reference_Tables!$G$5,Reference_Tables!$G$4))) -> Diamond | O65: =VLOOKUP(Sales_Data_Analysis[[#This Row],[Gross_Sales]],Table3[],2,TRUE) -> 0.05 | P65: =EOMONTH(Sales_Data_Analysis[[#This Row],[Order_Date]],1) -> 43434 | Q65: =NETWORKDAYS(Sales_Data_Analysis[[#This Row],[Order_Date]],Sales_Data_Analysis[[#This Row],[Delivery_Date]]) -> -165
A66: ORD-020 | B66: 2018-07-30 | C66: =MONTH(Sales_Data_Analysis[[#This Row],[Order_Date]]) -> 7 | D66: =YEAR(Sales_Data_Analysis[[#This Row],[Order_Date]]) -> 2018 | E66: 43169 | F66: Australia (Oceania) | G66: Australia | H66: Oceania | I66: Tablets | J66: samsung GALAXY tab | K66: 0 | L66: 876 | M66: 876 | N66: =IF(Sales_Data_Analysis[[#This Row],[Profit]]<=Reference_Tables!$F$7,Reference_Tables!$G$7,IF(Sales_Data_Analysis[[#This Row],[Profit]]<=Reference_Tables!$F$6,Reference_Tables!$G$6,IF(Sales_Data_Analysis[[#This Row],[Profit]]<=Reference_Tables!$F$5,Reference_Tables!$G$5,Reference_Tables!$G$4))) -> Platinum | O66: =VLOOKUP(Sales_Data_Analysis[[#This Row],[Gross_Sales]],Table3[],2,TRUE) -> 0.02 | P66: =EOMONTH(Sales_Data_Analysis[[#This Row],[Order_Date]],1) -> 43343 | Q66: =NETWORKDAYS(Sales_Data_Analysis[[#This Row],[Order_Date]],Sales_Data_Analysis[[#This Row],[Delivery_Date]]) -> -101
A67: ORD-024 | B67: 2018-09-14 | C67: =MONTH(Sales_Data_Analysis[[#This Row],[Order_Date]]) -> 9 | D67: =YEAR(Sales_Data_Analysis[[#This Row],[Order_Date]]) -> 2018 | E67: 43170 | F67: USA (North America) | G67: USA | H67: North America | I67: Accessories | J67: KEYchron keyboard | K67: 0 | L67: 878 | M67: 878 | N67: =IF(Sales_Data_Analysis[[#This Row],[Profit]]<=Reference_Tables!$F$7,Reference_Tables!$G$7,IF(Sales_Data_Analysis[[#This Row],[Profit]]<=Reference_Tables!$F$6,Reference_Tables!$G$6,IF(Sales_Data_Analysis[[#This Row],[Profit]]<=Reference_Tables!$F$5,Reference_Tables!$G$5,Reference_Tables!$G$4))) -> Platinum | O67: =VLOOKUP(Sales_Data_Analysis[[#This Row],[Gross_Sales]],Table3[],2,TRUE) -> 0.02 | P67: =EOMONTH(Sales_Data_Analysis[[#This Row],[Order_Date]],1) -> 43404 | Q67: =NETWORKDAYS(Sales_Data_Analysis[[#This Row],[Order_Date]],Sales_Data_Analysis[[#This Row],[Delivery_Date]]) -> -135
A68: ORD-025 | B68: 2019-09-09 | C68: =MONTH(Sales_Data_Analysis[[#This Row],[Order_Date]]) -> 9 | D68: =YEAR(Sales_Data_Analysis[[#This Row],[Order_Date]]) -> 2019 | E68: 43171 | F68: India (Asia) | G68: India | H68: Asia | I68: PCs | J68: Dell INSPIRON | K68: 0 | L68: 274 | M68: 274 | N68: =IF(Sales_Data_Analysis[[#This Row],[Profit]]<=Reference_Tables!$F$7,Reference_Tables!$G$7,IF(Sales_Data_Analysis[[#This Row],[Profit]]<=Reference_Tables!$F$6,Reference_Tables!$G$6,IF(Sales_Data_Analysis[[#This Row],[Profit]]<=Reference_Tables!$F$5,Reference_Tables!$G$5,Reference_Tables!$G$4))) -> Silver | O68: =VLOOKUP(Sales_Data_Analysis[[#This Row],[Gross_Sales]],Table3[],2,TRUE) -> 0 | P68: =EOMONTH(Sales_Data_Analysis[[#This Row],[Order_Date]],1) -> 43769 | Q68: =NETWORKDAYS(Sales_Data_Analysis[[#This Row],[Order_Date]],Sales_Data_Analysis[[#This Row],[Delivery_Date]]) -> -391
... A120: ORD-115 | B120: 2018-11-06 | C120: =MONTH(Sales_Data_Analysis[[#This Row],[Order_Date]]) -> 11 | D120: =YEAR(Sales_Data_Analysis[[#This Row],[Order_Date]]) -> 2018 | E120: 43223 | F120: India (Asia) | G120: India | H120: Asia | I120: Laptops | J120: mAcBoOk pRo 16 | K120: 0 | L120: 931 | M120: 931 | N120: =IF(Sales_Data_Analysis[[#This Row],[Profit]]<=Reference_Tables!$F$7,Reference_Tables!$G$7,IF(Sales_Data_Analysis[[#This Row],[Profit]]<=Reference_Tables!$F$6,Reference_Tables!$G$6,IF(Sales_Data_Analysis[[#This Row],[Profit]]<=Reference_Tables!$F$5,Reference_Tables!$G$5,Reference_Tables!$G$4))) -> Diamond | O120: =VLOOKUP(Sales_Data_Analysis[[#This Row],[Gross_Sales]],Table3[],2,TRUE) -> 0.02 | P120: =EOMONTH(Sales_Data_Analysis[[#This Row],[Order_Date]],1) -> 43465 | Q120: =NETWORKDAYS(Sales_Data_Analysis[[#This Row],[Order_Date]],Sales_Data_Analysis[[#This Row],[Delivery_Date]]) -> -134

Sheet Reference_Tables
A3: Commission Tiers (Sales_Volume | B3: Rate): | E3: Min_Profit | F3: Max_Profit | G3: Status
A4: 0 | B4: 0 | E4: 900 | F4: - | G4: Diamond
A5: 500 | B5: 0.02 | E5: 600 | F5: 900 | G5: Platinum
A6: 1000 | B6: 0.05 | E6: 300 | F6: 600 | G6: Gold
A7: 1500 | B7: 0.1 | E7: 0 | F7: 300 | G7: Silver
A9: Project Managers | B9: Manager):
A10: Macbook Pro 16 | B10: Alice Smith
A11: Dell Xps 15 | B11: Bob Johnson
A12: Lenovo Thinkpad | B12: Charlie Davis
A13: Hp Spectre X360 | B13: Diana Prince
A14: Iphone 14 Pro | B14: Eve Adams
A15: Samsung Galaxy S23 | B15: Frank Castle
A16: Google Pixel 7 | B16: George King
A17: Oneplus 11 | B17: Hannah Baker
A18: Dell Inspiron | B18: Ian Wright
A19: Hp Pavilion | B19: Jane Doe
A20: Lenovo Legion | B20: Kevin Hart
... A27: Keychron Keyboard | B27: Rachel Green

Sheet Quick_Analysis
R1: List_of_Regions | S1: List of Categories
S2: Laptops
R3: Europe | S3: Mobile Phones
C4: Category | D4: Region | E4: Units_sold | F4: Profit | R4: North America | S4: Tablets
C5: Mobile Phones | D5: North America | E5: =COUNTIFS(Sales_Data_Analysis!I:I,Quick_Analysis!C5,Sales_Data_Analysis!H:H,Quick_Analysis!D5) -> 2 | F5: =SUMIFS(Sales_Data_Analysis!M:M,Sales_Data_Analysis!H:H,Quick_Analysis!D5,Sales_Data_Analysis!I:I,Quick_Analysis!C5) -> 1243 | R5: Asia | S5: Accessories
S6: PCs

Sheet Pivot_Table_Gross_Sales_By_Date
A4: Row Labels | B4: Sum of Gross_Sales
A5: 2018 | B5: 14925
A6: Q1 | B6: 6708
A7: Q2 | B7: 3316
A8: Q3 | B8: 3267
A9: Q4 | B9: 1634
A10: 2019 | B10: 5660
A11: Q1 | B11: 1457
A12: Q2 | B12: 2193
A13: Q3 | B13: 2010
A14: Grand Total | B14: 20585

Sheet Pivot_Table_Average_Profit_Per_
A3: Row Labels | B3: Average of Profit
A4: Laptops | B4: 674.86957
